README.md
setup.py
distl/__init__.py
distl/distl.py
distl/stats_custom.py
distl.egg-info/PKG-INFO
distl.egg-info/SOURCES.txt
distl.egg-info/dependency_links.txt
distl.egg-info/requires.txt
distl.egg-info/top_level.txt